aioquic/__init__.py
aioquic/_buffer.abi3.so
aioquic/_buffer.c
aioquic/_buffer.pyi
aioquic/_crypto.abi3.so
aioquic/_crypto.c
aioquic/_crypto.pyi
aioquic/buffer.py
aioquic/py.typed
aioquic/tls.py
aioquic/asyncio/__init__.py
aioquic/asyncio/client.py
aioquic/asyncio/protocol.py
aioquic/asyncio/server.py
aioquic/h0/__init__.py
aioquic/h0/connection.py
aioquic/h3/__init__.py
aioquic/h3/connection.py
aioquic/h3/events.py
aioquic/h3/exceptions.py
aioquic/quic/__init__.py
aioquic/quic/configuration.py
aioquic/quic/connection.py
aioquic/quic/crypto.py
aioquic/quic/events.py
aioquic/quic/logger.py
aioquic/quic/packet.py
aioquic/quic/packet_builder.py
aioquic/quic/rangeset.py
aioquic/quic/recovery.py
aioquic/quic/retry.py
aioquic/quic/stream.py
aioquic/quic/congestion/__init__.py
aioquic/quic/congestion/base.py
aioquic/quic/congestion/cubic.py
aioquic/quic/congestion/reno.py
aioquic-1.3.0.dist-info/METADATA
aioquic-1.3.0.dist-info/WHEEL
aioquic-1.3.0.dist-info/top_level.txt
aioquic-1.3.0.dist-info/RECORD
aioquic-1.3.0.dist-info/licenses/LICENSE
