Metadata-Version: 2.4
Name: aioquic
Version: 1.3.0
Summary: An implementation of QUIC and HTTP/3
Author-email: Jeremy Lainé <jeremy.laine@m4x.org>
License-Expression: BSD-3-Clause
Project-URL: Homepage, https://github.com/aiortc/aioquic
Project-URL: Changelog, https://aioquic.readthedocs.io/en/stable/changelog.html
Project-URL: Documentation, https://aioquic.readthedocs.io/
Classifier: Development Status :: 5 - Production/Stable
Classifier: Environment :: Web Environment
Classifier: Intended Audience :: Developers
Classifier: Operating System :: OS Independent
Classifier: Programming Language :: Python
Classifier: Programming Language :: Python :: 3
Classifier: Programming Language :: Python :: 3.10
Classifier: Programming Language :: Python :: 3.11
Classifier: Programming Language :: Python :: 3.12
Classifier: Programming Language :: Python :: 3.13
Classifier: Programming Language :: Python :: 3.14
Classifier: Topic :: Internet :: WWW/HTTP
Requires-Python: >=3.10
License-File: LICENSE
Requires-Dist: certifi
Requires-Dist: cryptography>=42.0.0
Requires-Dist: pylsqpack<0.4.0,>=0.3.3
Requires-Dist: pyopenssl>=24
Requires-Dist: service-identity>=24.1.0
Provides-Extra: dev
Requires-Dist: coverage[toml]>=7.2.2; extra == "dev"
Dynamic: license-file
